README.md
setup.py
simpyder/__init__.py
simpyder/__version__.py
simpyder/config.py
simpyder/scheduler.py
simpyder/utils.py
simpyder.egg-info/PKG-INFO
simpyder.egg-info/SOURCES.txt
simpyder.egg-info/dependency_links.txt
simpyder.egg-info/requires.txt
simpyder.egg-info/top_level.txt
simpyder/spiders/__init__.py
simpyder/spiders/asyn_spider.py
simpyder/spiders/spiders.py