Metadata-Version: 2.1
Name: simpyder
Version: 0.1.5
Summary: Distributed multithreading universal crawler
Home-page: https://github.com/Jannchie/simpyder
Author: Jannchie
Author-email: jannchie@gmail.com
Maintainer: Jannchie
Maintainer-email: jannchie@gmail.com
License: MIT License
Platform: all
Classifier: Programming Language :: Python :: 3
Classifier: License :: OSI Approved :: MIT License
Classifier: Operating System :: OS Independent
Requires-Python: >=3.6
